[
    {
        "crates": 3,
        "database_loaded_time": "3.924953289s",
        "declarations": 3288,
        "expressions": 142365,
        "functions": 2759,
        "inferenece_time": "11.552724097s",
        "item_collection_time": "18.145748558s",
        "modules": 213,
        "partial_unknown_types": 1671,
        "project_name": "./rustc-perf/collector/benchmarks/cargo/",
        "roots": 0,
        "total_time": "29.698480755s",
        "type_mismatches": 113,
        "unknown_types": 2675
    },
    {
        "crates": 63,
        "database_loaded_time": "532.952955ms",
        "declarations": 1660,
        "expressions": 92894,
        "functions": 1345,
        "inferenece_time": "7.700458485s",
        "item_collection_time": "6.263444234s",
        "modules": 134,
        "partial_unknown_types": 333,
        "project_name": "./rustc-perf/collector/benchmarks/clap-rs/",
        "roots": 0,
        "total_time": "13.963913019s",
        "type_mismatches": 41,
        "unknown_types": 818
    },
    {
        "crates": 21,
        "database_loaded_time": "1.473642676s",
        "declarations": 3955,
        "expressions": 198255,
        "functions": 2991,
        "inferenece_time": "13.523221474s",
        "item_collection_time": "11.016642918s",
        "modules": 315,
        "partial_unknown_types": 7005,
        "project_name": "./rustc-perf/collector/benchmarks/cranelift-codegen/",
        "roots": 0,
        "total_time": "24.539875392s",
        "type_mismatches": 46,
        "unknown_types": 4251
    },
    {
        "crates": 1,
        "database_loaded_time": "537.135315ms",
        "declarations": 504,
        "expressions": 8445,
        "functions": 257,
        "inferenece_time": "5.531930772s",
        "item_collection_time": "3.116691182s",
        "modules": 55,
        "partial_unknown_types": 791,
        "project_name": "./rustc-perf/collector/benchmarks/futures/",
        "roots": 0,
        "total_time": "8.648632154s",
        "type_mismatches": 18,
        "unknown_types": 488
    },
    {
        "crates": 1,
        "database_loaded_time": "161.825305ms",
        "declarations": 1,
        "expressions": 10,
        "functions": 1,
        "inferenece_time": "1.039822806s",
        "item_collection_time": "2.835606348s",
        "modules": 1,
        "partial_unknown_types": 0,
        "project_name": "./rustc-perf/collector/benchmarks/helloworld/",
        "roots": 0,
        "total_time": "3.875438454s",
        "type_mismatches": 0,
        "unknown_types": 0
    },
    {
        "crates": 2,
        "database_loaded_time": "813.593942ms",
        "declarations": 348,
        "expressions": 16088,
        "functions": 255,
        "inferenece_time": "3.008177514s",
        "item_collection_time": "10.619833253s",
        "modules": 28,
        "partial_unknown_types": 147,
        "project_name": "./rustc-perf/collector/benchmarks/html5ever/",
        "roots": 0,
        "total_time": "13.628020867s",
        "type_mismatches": 8,
        "unknown_types": 45
    },
    {
        "crates": 1,
        "database_loaded_time": "2.322939993s",
        "declarations": 1048,
        "expressions": 29500,
        "functions": 728,
        "inferenece_time": "4.279215546s",
        "item_collection_time": "10.206385429s",
        "modules": 126,
        "partial_unknown_types": 653,
        "project_name": "./rustc-perf/collector/benchmarks/hyper/",
        "roots": 0,
        "total_time": "14.485610875s",
        "type_mismatches": 16,
        "unknown_types": 113
    },
    {
        "crates": 9,
        "database_loaded_time": "1.10676651s",
        "declarations": 523,
        "expressions": 9168,
        "functions": 358,
        "inferenece_time": "2.56902443s",
        "item_collection_time": "11.379398192s",
        "modules": 56,
        "partial_unknown_types": 141,
        "project_name": "./rustc-perf/collector/benchmarks/syn/",
        "roots": 0,
        "total_time": "13.948473322s",
        "type_mismatches": 4,
        "unknown_types": 156
    }
]