[
    {
        "crates": 3,
        "database_loaded_time": "2.743632705s",
        "declarations": 3292,
        "expressions": 124343,
        "functions": 2763,
        "inferenece_time": "27.046507716s",
        "item_collection_time": "16.756909957s",
        "modules": 213,
        "partial_unknown_types": 3076,
        "project_name": "./rustc-perf/collector/benchmarks/cargo/",
        "roots": 132,
        "total_time": "43.803429274s",
        "type_mismatches": 200,
        "unknown_types": 2989
    },
    {
        "crates": 63,
        "database_loaded_time": "871.423158ms",
        "declarations": 1563,
        "expressions": 63625,
        "functions": 1279,
        "inferenece_time": "25.046250693s",
        "item_collection_time": "11.680274317s",
        "modules": 115,
        "partial_unknown_types": 2312,
        "project_name": "./rustc-perf/collector/benchmarks/clap-rs/",
        "roots": 77,
        "total_time": "36.726534711s",
        "type_mismatches": 32,
        "unknown_types": 2741
    },
    {
        "crates": 21,
        "database_loaded_time": "6.770219347s",
        "declarations": 3957,
        "expressions": 151434,
        "functions": 2993,
        "inferenece_time": "21.097795098s",
        "item_collection_time": "10.884206424s",
        "modules": 315,
        "partial_unknown_types": 7203,
        "project_name": "./rustc-perf/collector/benchmarks/cranelift-codegen/",
        "roots": 132,
        "total_time": "31.982011623s",
        "type_mismatches": 350,
        "unknown_types": 7697
    },
    {
        "crates": 1,
        "database_loaded_time": "607.546631ms",
        "declarations": 504,
        "expressions": 6986,
        "functions": 257,
        "inferenece_time": "5.094774345s",
        "item_collection_time": "3.233015179s",
        "modules": 55,
        "partial_unknown_types": 1574,
        "project_name": "./rustc-perf/collector/benchmarks/futures/",
        "roots": 16,
        "total_time": "8.327798424s",
        "type_mismatches": 197,
        "unknown_types": 650
    },
    {
        "crates": 1,
        "database_loaded_time": "73.902851ms",
        "declarations": 1,
        "expressions": 10,
        "functions": 1,
        "inferenece_time": "3.402963596s",
        "item_collection_time": "3.156624372s",
        "modules": 1,
        "partial_unknown_types": 0,
        "project_name": "./rustc-perf/collector/benchmarks/helloworld/",
        "roots": 15,
        "total_time": "6.559597769s",
        "type_mismatches": 0,
        "unknown_types": 0
    },
    {
        "crates": 2,
        "database_loaded_time": "900.81167ms",
        "declarations": 348,
        "expressions": 11344,
        "functions": 255,
        "inferenece_time": "10.962501048s",
        "item_collection_time": "9.894151234s",
        "modules": 28,
        "partial_unknown_types": 218,
        "project_name": "./rustc-perf/collector/benchmarks/html5ever/",
        "roots": 56,
        "total_time": "20.856661882s",
        "type_mismatches": 65,
        "unknown_types": 393
    },
    {
        "crates": 1,
        "database_loaded_time": "616.256368ms",
        "declarations": 1180,
        "error": "fail to parse output",
        "functions": 819,
        "item_collection_time": "9.665837193s",
        "modules": 167,
        "project_name": "./rustc-perf/collector/benchmarks/hyper/",
        "roots": 51
    },
    {
        "crates": 9,
        "database_loaded_time": "1.167271264s",
        "declarations": 1244,
        "expressions": 19778,
        "functions": 995,
        "inferenece_time": "12.748615507s",
        "item_collection_time": "10.626851552s",
        "modules": 65,
        "partial_unknown_types": 2223,
        "project_name": "./rustc-perf/collector/benchmarks/syn/",
        "roots": 58,
        "total_time": "23.375476459s",
        "type_mismatches": 28,
        "unknown_types": 3798
    }
]