[
    {
        "crates": 3,
        "database_loaded_time": "2.674053139s",
        "declarations": 3292,
        "expressions": 141718,
        "functions": 2763,
        "inferenece_time": "26.683208425s",
        "item_collection_time": "15.299276518s",
        "modules": 213,
        "partial_unknown_types": 2851,
        "project_name": "./rustc-perf/collector/benchmarks/cargo/",
        "roots": 132,
        "total_time": "41.982495044s",
        "type_mismatches": 351,
        "unknown_types": 2708
    },
    {
        "crates": 63,
        "database_loaded_time": "858.015189ms",
        "declarations": 1563,
        "expressions": 85862,
        "functions": 1279,
        "inferenece_time": "18.703212416s",
        "item_collection_time": "10.495800009s",
        "modules": 115,
        "partial_unknown_types": 3090,
        "project_name": "./rustc-perf/collector/benchmarks/clap-rs/",
        "roots": 77,
        "total_time": "29.199022726s",
        "type_mismatches": 33,
        "unknown_types": 2653
    },
    {
        "crates": 21,
        "database_loaded_time": "1.332544772s",
        "declarations": 3957,
        "expressions": 200206,
        "functions": 2993,
        "inferenece_time": "21.679261581s",
        "item_collection_time": "9.849404478s",
        "modules": 315,
        "partial_unknown_types": 12190,
        "project_name": "./rustc-perf/collector/benchmarks/cranelift-codegen/",
        "roots": 132,
        "total_time": "31.52867476s",
        "type_mismatches": 192,
        "unknown_types": 8002
    },
    {
        "crates": 1,
        "database_loaded_time": "380.906615ms",
        "declarations": 504,
        "expressions": 8349,
        "functions": 257,
        "inferenece_time": "4.837197566s",
        "item_collection_time": "2.855158665s",
        "modules": 55,
        "partial_unknown_types": 1611,
        "project_name": "./rustc-perf/collector/benchmarks/futures/",
        "roots": 16,
        "total_time": "7.692365431s",
        "type_mismatches": 43,
        "unknown_types": 692
    },
    {
        "crates": 1,
        "database_loaded_time": "62.59502ms",
        "declarations": 1,
        "expressions": 10,
        "functions": 1,
        "inferenece_time": "3.28919057s",
        "item_collection_time": "2.710335342s",
        "modules": 1,
        "partial_unknown_types": 0,
        "project_name": "./rustc-perf/collector/benchmarks/helloworld/",
        "roots": 15,
        "total_time": "5.999535312s",
        "type_mismatches": 0,
        "unknown_types": 0
    },
    {
        "crates": 2,
        "database_loaded_time": "351.428019ms",
        "declarations": 348,
        "expressions": 15097,
        "functions": 255,
        "inferenece_time": "10.182983885s",
        "item_collection_time": "8.897679232s",
        "modules": 28,
        "partial_unknown_types": 279,
        "project_name": "./rustc-perf/collector/benchmarks/html5ever/",
        "roots": 56,
        "total_time": "19.080672617s",
        "type_mismatches": 16,
        "unknown_types": 334
    },
    {
        "crates": 1,
        "database_loaded_time": "623.109162ms",
        "declarations": 1180,
        "expressions": 32860,
        "functions": 819,
        "inferenece_time": "11.426626585s",
        "item_collection_time": "8.716592016s",
        "modules": 167,
        "partial_unknown_types": 2125,
        "project_name": "./rustc-perf/collector/benchmarks/hyper/",
        "roots": 51,
        "total_time": "20.143228501s",
        "type_mismatches": 226,
        "unknown_types": 1292
    },
    {
        "crates": 9,
        "database_loaded_time": "647.138288ms",
        "declarations": 1244,
        "expressions": 22227,
        "functions": 995,
        "inferenece_time": "12.33864027s",
        "item_collection_time": "9.539199889s",
        "modules": 65,
        "partial_unknown_types": 2338,
        "project_name": "./rustc-perf/collector/benchmarks/syn/",
        "roots": 58,
        "total_time": "21.87784936s",
        "type_mismatches": 28,
        "unknown_types": 4167
    }
]