[
    {
        "crates": 3,
        "database_loaded_time": "2.66632256s",
        "declarations": 3292,
        "expressions": 141718,
        "functions": 2763,
        "inferenece_time": "25.836967129s",
        "item_collection_time": "14.958607167s",
        "modules": 213,
        "partial_unknown_types": 2849,
        "project_name": "./rustc-perf/collector/benchmarks/cargo/",
        "roots": 132,
        "total_time": "40.795583796s",
        "type_mismatches": 351,
        "unknown_types": 2706
    },
    {
        "crates": 63,
        "database_loaded_time": "493.196544ms",
        "declarations": 1563,
        "expressions": 85862,
        "functions": 1279,
        "inferenece_time": "17.833083887s",
        "item_collection_time": "10.309585798s",
        "modules": 115,
        "partial_unknown_types": 3090,
        "project_name": "./rustc-perf/collector/benchmarks/clap-rs/",
        "roots": 77,
        "total_time": "28.142678585s",
        "type_mismatches": 33,
        "unknown_types": 2653
    },
    {
        "crates": 21,
        "database_loaded_time": "1.677657876s",
        "declarations": 3957,
        "expressions": 200206,
        "functions": 2993,
        "inferenece_time": "20.811625577s",
        "item_collection_time": "9.574873109s",
        "modules": 315,
        "partial_unknown_types": 12190,
        "project_name": "./rustc-perf/collector/benchmarks/cranelift-codegen/",
        "roots": 132,
        "total_time": "30.386507386s",
        "type_mismatches": 170,
        "unknown_types": 8002
    },
    {
        "crates": 1,
        "database_loaded_time": "368.889074ms",
        "declarations": 504,
        "expressions": 8349,
        "functions": 257,
        "inferenece_time": "4.751874509s",
        "item_collection_time": "2.754549426s",
        "modules": 55,
        "partial_unknown_types": 1609,
        "project_name": "./rustc-perf/collector/benchmarks/futures/",
        "roots": 16,
        "total_time": "7.506432535s",
        "type_mismatches": 43,
        "unknown_types": 694
    },
    {
        "crates": 1,
        "database_loaded_time": "63.604286ms",
        "declarations": 1,
        "expressions": 10,
        "functions": 1,
        "inferenece_time": "3.156124318s",
        "item_collection_time": "2.675543431s",
        "modules": 1,
        "partial_unknown_types": 0,
        "project_name": "./rustc-perf/collector/benchmarks/helloworld/",
        "roots": 15,
        "total_time": "5.831676249s",
        "type_mismatches": 0,
        "unknown_types": 0
    },
    {
        "crates": 2,
        "database_loaded_time": "407.482179ms",
        "declarations": 348,
        "expressions": 15097,
        "functions": 255,
        "inferenece_time": "9.687000588s",
        "item_collection_time": "8.557214004s",
        "modules": 28,
        "partial_unknown_types": 279,
        "project_name": "./rustc-perf/collector/benchmarks/html5ever/",
        "roots": 56,
        "total_time": "18.244223492s",
        "type_mismatches": 16,
        "unknown_types": 334
    },
    {
        "crates": 1,
        "database_loaded_time": "806.70129ms",
        "declarations": 1180,
        "expressions": 32860,
        "functions": 819,
        "inferenece_time": "11.243975071s",
        "item_collection_time": "8.389886156s",
        "modules": 167,
        "partial_unknown_types": 2125,
        "project_name": "./rustc-perf/collector/benchmarks/hyper/",
        "roots": 51,
        "total_time": "19.633870427s",
        "type_mismatches": 226,
        "unknown_types": 1292
    },
    {
        "crates": 9,
        "database_loaded_time": "651.059762ms",
        "declarations": 1244,
        "expressions": 22227,
        "functions": 995,
        "inferenece_time": "12.120522478s",
        "item_collection_time": "9.202234848s",
        "modules": 65,
        "partial_unknown_types": 2338,
        "project_name": "./rustc-perf/collector/benchmarks/syn/",
        "roots": 58,
        "total_time": "21.322766626s",
        "type_mismatches": 28,
        "unknown_types": 4167
    }
]