[
    {
        "crates": 3,
        "database_loaded_time": "4.200319971s",
        "declarations": 3288,
        "expressions": 142365,
        "functions": 2759,
        "inferenece_time": "9.661528758s",
        "item_collection_time": "17.743069015s",
        "modules": 213,
        "partial_unknown_types": 1671,
        "project_name": "./rustc-perf/collector/benchmarks/cargo/",
        "roots": 0,
        "total_time": "27.404863778s",
        "type_mismatches": 113,
        "unknown_types": 2675
    },
    {
        "crates": 63,
        "database_loaded_time": "783.98658ms",
        "declarations": 1660,
        "expressions": 92894,
        "functions": 1345,
        "inferenece_time": "6.396262568s",
        "item_collection_time": "6.299349818s",
        "modules": 134,
        "partial_unknown_types": 333,
        "project_name": "./rustc-perf/collector/benchmarks/clap-rs/",
        "roots": 0,
        "total_time": "12.69584659s",
        "type_mismatches": 41,
        "unknown_types": 818
    },
    {
        "crates": 21,
        "database_loaded_time": "2.446799894s",
        "declarations": 3955,
        "expressions": 198255,
        "functions": 2991,
        "inferenece_time": "11.032326129s",
        "item_collection_time": "11.062835621s",
        "modules": 315,
        "partial_unknown_types": 7005,
        "project_name": "./rustc-perf/collector/benchmarks/cranelift-codegen/",
        "roots": 0,
        "total_time": "22.095336353s",
        "type_mismatches": 46,
        "unknown_types": 4251
    },
    {
        "crates": 1,
        "database_loaded_time": "628.227707ms",
        "declarations": 504,
        "expressions": 8445,
        "functions": 257,
        "inferenece_time": "4.571592496s",
        "item_collection_time": "2.995559062s",
        "modules": 55,
        "partial_unknown_types": 791,
        "project_name": "./rustc-perf/collector/benchmarks/futures/",
        "roots": 0,
        "total_time": "7.567280559s",
        "type_mismatches": 18,
        "unknown_types": 488
    },
    {
        "crates": 1,
        "database_loaded_time": "154.969871ms",
        "declarations": 1,
        "expressions": 10,
        "functions": 1,
        "inferenece_time": "1.067990292s",
        "item_collection_time": "2.853907005s",
        "modules": 1,
        "partial_unknown_types": 0,
        "project_name": "./rustc-perf/collector/benchmarks/helloworld/",
        "roots": 0,
        "total_time": "3.921995998s",
        "type_mismatches": 0,
        "unknown_types": 0
    },
    {
        "crates": 2,
        "database_loaded_time": "690.576317ms",
        "declarations": 348,
        "expressions": 16088,
        "functions": 255,
        "inferenece_time": "2.699373686s",
        "item_collection_time": "10.434922308s",
        "modules": 28,
        "partial_unknown_types": 147,
        "project_name": "./rustc-perf/collector/benchmarks/html5ever/",
        "roots": 0,
        "total_time": "13.134754699s",
        "type_mismatches": 8,
        "unknown_types": 45
    },
    {
        "crates": 1,
        "database_loaded_time": "997.182922ms",
        "declarations": 1048,
        "expressions": 29500,
        "functions": 728,
        "inferenece_time": "3.716604396s",
        "item_collection_time": "10.456614245s",
        "modules": 126,
        "partial_unknown_types": 653,
        "project_name": "./rustc-perf/collector/benchmarks/hyper/",
        "roots": 0,
        "total_time": "14.173762347s",
        "type_mismatches": 16,
        "unknown_types": 113
    },
    {
        "crates": 9,
        "database_loaded_time": "945.227873ms",
        "declarations": 523,
        "expressions": 9168,
        "functions": 358,
        "inferenece_time": "2.260364594s",
        "item_collection_time": "11.026440263s",
        "modules": 56,
        "partial_unknown_types": 141,
        "project_name": "./rustc-perf/collector/benchmarks/syn/",
        "roots": 0,
        "total_time": "13.288078974s",
        "type_mismatches": 4,
        "unknown_types": 156
    }
]