[
    {
        "crates": 3,
        "database_loaded_time": "2.997847216s",
        "declarations": 3292,
        "expressions": 141718,
        "functions": 2763,
        "inferenece_time": "26.100667879s",
        "item_collection_time": "14.877467269s",
        "modules": 213,
        "partial_unknown_types": 2845,
        "project_name": "./rustc-perf/collector/benchmarks/cargo/",
        "roots": 132,
        "total_time": "40.978144448s",
        "type_mismatches": 355,
        "unknown_types": 2705
    },
    {
        "crates": 63,
        "database_loaded_time": "1.048781245s",
        "declarations": 1563,
        "expressions": 85862,
        "functions": 1279,
        "inferenece_time": "18.102760055s",
        "item_collection_time": "10.495268758s",
        "modules": 115,
        "partial_unknown_types": 3090,
        "project_name": "./rustc-perf/collector/benchmarks/clap-rs/",
        "roots": 77,
        "total_time": "28.598038113s",
        "type_mismatches": 33,
        "unknown_types": 2653
    },
    {
        "crates": 21,
        "database_loaded_time": "1.753522598s",
        "declarations": 3957,
        "expressions": 200206,
        "functions": 2993,
        "inferenece_time": "20.847540195s",
        "item_collection_time": "9.641803081s",
        "modules": 315,
        "partial_unknown_types": 12190,
        "project_name": "./rustc-perf/collector/benchmarks/cranelift-codegen/",
        "roots": 132,
        "total_time": "30.489352176s",
        "type_mismatches": 170,
        "unknown_types": 8002
    },
    {
        "crates": 1,
        "database_loaded_time": "635.506996ms",
        "declarations": 504,
        "expressions": 8349,
        "functions": 257,
        "inferenece_time": "4.886247745s",
        "item_collection_time": "2.845935263s",
        "modules": 55,
        "partial_unknown_types": 1611,
        "project_name": "./rustc-perf/collector/benchmarks/futures/",
        "roots": 16,
        "total_time": "7.732192308s",
        "type_mismatches": 43,
        "unknown_types": 692
    },
    {
        "crates": 1,
        "database_loaded_time": "63.677613ms",
        "declarations": 1,
        "expressions": 10,
        "functions": 1,
        "inferenece_time": "3.203928601s",
        "item_collection_time": "2.726359209s",
        "modules": 1,
        "partial_unknown_types": 0,
        "project_name": "./rustc-perf/collector/benchmarks/helloworld/",
        "roots": 15,
        "total_time": "5.93029661s",
        "type_mismatches": 0,
        "unknown_types": 0
    },
    {
        "crates": 2,
        "database_loaded_time": "813.45424ms",
        "declarations": 348,
        "expressions": 15097,
        "functions": 255,
        "inferenece_time": "9.993104899s",
        "item_collection_time": "8.78882176s",
        "modules": 28,
        "partial_unknown_types": 279,
        "project_name": "./rustc-perf/collector/benchmarks/html5ever/",
        "roots": 56,
        "total_time": "18.781936259s",
        "type_mismatches": 16,
        "unknown_types": 334
    },
    {
        "crates": 1,
        "database_loaded_time": "1.250111777s",
        "declarations": 1180,
        "expressions": 32860,
        "functions": 819,
        "inferenece_time": "11.129031809s",
        "item_collection_time": "8.667409875s",
        "modules": 167,
        "partial_unknown_types": 2125,
        "project_name": "./rustc-perf/collector/benchmarks/hyper/",
        "roots": 51,
        "total_time": "19.796450684s",
        "type_mismatches": 226,
        "unknown_types": 1292
    },
    {
        "crates": 9,
        "database_loaded_time": "1.080811807s",
        "declarations": 1244,
        "expressions": 22227,
        "functions": 995,
        "inferenece_time": "12.277203214s",
        "item_collection_time": "9.407335655s",
        "modules": 65,
        "partial_unknown_types": 2338,
        "project_name": "./rustc-perf/collector/benchmarks/syn/",
        "roots": 58,
        "total_time": "21.684549269s",
        "type_mismatches": 28,
        "unknown_types": 4167
    }
]