[
    {
        "crates": 3,
        "database_loaded_time": "2.181631098s",
        "declarations": 3289,
        "expressions": 142419,
        "functions": 2760,
        "inferenece_time": "26.204895514s",
        "item_collection_time": "15.179648953s",
        "modules": 213,
        "partial_unknown_types": 628,
        "project_name": "./rustc-perf/collector/benchmarks/cargo/",
        "roots": 127,
        "total_time": "41.384554267s",
        "type_mismatches": 264,
        "unknown_types": 375
    },
    {
        "crates": 63,
        "database_loaded_time": "906.354015ms",
        "declarations": 1665,
        "expressions": 96493,
        "functions": 1351,
        "inferenece_time": "18.161714818s",
        "item_collection_time": "10.591171338s",
        "modules": 133,
        "partial_unknown_types": 434,
        "project_name": "./rustc-perf/collector/benchmarks/clap-rs/",
        "roots": 72,
        "total_time": "28.752896256s",
        "type_mismatches": 189,
        "unknown_types": 866
    },
    {
        "crates": 21,
        "database_loaded_time": "1.228016829s",
        "declarations": 3955,
        "expressions": 198251,
        "functions": 2991,
        "inferenece_time": "21.181981842s",
        "item_collection_time": "9.30654943s",
        "modules": 315,
        "partial_unknown_types": 7822,
        "project_name": "./rustc-perf/collector/benchmarks/cranelift-codegen/",
        "roots": 127,
        "total_time": "30.488540673s",
        "type_mismatches": 262,
        "unknown_types": 4639
    },
    {
        "crates": 1,
        "database_loaded_time": "351.654981ms",
        "declarations": 504,
        "expressions": 8443,
        "functions": 257,
        "inferenece_time": "6.722794047s",
        "item_collection_time": "2.387231518s",
        "modules": 55,
        "partial_unknown_types": 811,
        "project_name": "./rustc-perf/collector/benchmarks/futures/",
        "roots": 11,
        "total_time": "9.110035165s",
        "type_mismatches": 19,
        "unknown_types": 501
    },
    {
        "crates": 1,
        "database_loaded_time": "110.01839ms",
        "declarations": 1,
        "expressions": 10,
        "functions": 1,
        "inferenece_time": "3.026999133s",
        "item_collection_time": "2.212505743s",
        "modules": 1,
        "partial_unknown_types": 0,
        "project_name": "./rustc-perf/collector/benchmarks/helloworld/",
        "roots": 10,
        "total_time": "5.239512976s",
        "type_mismatches": 0,
        "unknown_types": 0
    },
    {
        "crates": 2,
        "database_loaded_time": "663.580039ms",
        "declarations": 348,
        "expressions": 16137,
        "functions": 255,
        "inferenece_time": "9.426989707s",
        "item_collection_time": "7.187779326s",
        "modules": 28,
        "partial_unknown_types": 164,
        "project_name": "./rustc-perf/collector/benchmarks/html5ever/",
        "roots": 51,
        "total_time": "16.614779033s",
        "type_mismatches": 52,
        "unknown_types": 55
    },
    {
        "crates": 1,
        "database_loaded_time": "747.53686ms",
        "declarations": 1180,
        "expressions": 32031,
        "functions": 819,
        "inferenece_time": "11.236560077s",
        "item_collection_time": "8.023471771s",
        "modules": 167,
        "partial_unknown_types": 918,
        "project_name": "./rustc-perf/collector/benchmarks/hyper/",
        "roots": 46,
        "total_time": "19.260041348s",
        "type_mismatches": 152,
        "unknown_types": 256
    },
    {
        "crates": 9,
        "database_loaded_time": "998.503887ms",
        "declarations": 1243,
        "expressions": 22038,
        "functions": 994,
        "inferenece_time": "11.603810912s",
        "item_collection_time": "9.052047228s",
        "modules": 65,
        "partial_unknown_types": 2367,
        "project_name": "./rustc-perf/collector/benchmarks/syn/",
        "roots": 53,
        "total_time": "20.65586764s",
        "type_mismatches": 95,
        "unknown_types": 4037
    }
]