[
    {
        "crates": 3,
        "database_loaded_time": "3.357358423s",
        "declarations": 3288,
        "expressions": 142365,
        "functions": 2759,
        "inferenece_time": "10.237835609s",
        "item_collection_time": "17.906959044s",
        "modules": 213,
        "partial_unknown_types": 1671,
        "project_name": "./rustc-perf/collector/benchmarks/cargo/",
        "roots": 0,
        "total_time": "28.144991459s",
        "type_mismatches": 113,
        "unknown_types": 2675
    },
    {
        "crates": 63,
        "database_loaded_time": "523.663012ms",
        "declarations": 1660,
        "expressions": 92894,
        "functions": 1345,
        "inferenece_time": "6.674171513s",
        "item_collection_time": "6.249829755s",
        "modules": 134,
        "partial_unknown_types": 333,
        "project_name": "./rustc-perf/collector/benchmarks/clap-rs/",
        "roots": 0,
        "total_time": "12.924206874s",
        "type_mismatches": 41,
        "unknown_types": 818
    },
    {
        "crates": 21,
        "database_loaded_time": "1.176329015s",
        "declarations": 3955,
        "expressions": 198255,
        "functions": 2991,
        "inferenece_time": "11.663797842s",
        "item_collection_time": "10.752333509s",
        "modules": 315,
        "partial_unknown_types": 7005,
        "project_name": "./rustc-perf/collector/benchmarks/cranelift-codegen/",
        "roots": 0,
        "total_time": "22.416293057s",
        "type_mismatches": 46,
        "unknown_types": 4251
    },
    {
        "crates": 1,
        "database_loaded_time": "598.703847ms",
        "declarations": 504,
        "expressions": 8445,
        "functions": 257,
        "inferenece_time": "4.876675635s",
        "item_collection_time": "3.07542046s",
        "modules": 55,
        "partial_unknown_types": 791,
        "project_name": "./rustc-perf/collector/benchmarks/futures/",
        "roots": 0,
        "total_time": "7.952222998s",
        "type_mismatches": 18,
        "unknown_types": 488
    },
    {
        "crates": 1,
        "database_loaded_time": "159.502023ms",
        "declarations": 1,
        "expressions": 10,
        "functions": 1,
        "inferenece_time": "1.073158258s",
        "item_collection_time": "2.898991859s",
        "modules": 1,
        "partial_unknown_types": 0,
        "project_name": "./rustc-perf/collector/benchmarks/helloworld/",
        "roots": 0,
        "total_time": "3.972283121s",
        "type_mismatches": 0,
        "unknown_types": 0
    },
    {
        "crates": 2,
        "database_loaded_time": "443.896476ms",
        "declarations": 348,
        "expressions": 16088,
        "functions": 255,
        "inferenece_time": "2.812292113s",
        "item_collection_time": "10.455516412s",
        "modules": 28,
        "partial_unknown_types": 147,
        "project_name": "./rustc-perf/collector/benchmarks/html5ever/",
        "roots": 0,
        "total_time": "13.268016031s",
        "type_mismatches": 8,
        "unknown_types": 45
    },
    {
        "crates": 1,
        "database_loaded_time": "912.17657ms",
        "declarations": 1048,
        "expressions": 29500,
        "functions": 728,
        "inferenece_time": "3.731569041s",
        "item_collection_time": "10.201992225s",
        "modules": 126,
        "partial_unknown_types": 653,
        "project_name": "./rustc-perf/collector/benchmarks/hyper/",
        "roots": 0,
        "total_time": "13.933928677s",
        "type_mismatches": 16,
        "unknown_types": 113
    },
    {
        "crates": 9,
        "database_loaded_time": "802.670446ms",
        "declarations": 523,
        "expressions": 9168,
        "functions": 358,
        "inferenece_time": "2.353996379s",
        "item_collection_time": "11.137323723s",
        "modules": 56,
        "partial_unknown_types": 141,
        "project_name": "./rustc-perf/collector/benchmarks/syn/",
        "roots": 0,
        "total_time": "13.491764715s",
        "type_mismatches": 4,
        "unknown_types": 156
    }
]