[
    {
        "crates": 2,
        "database_loaded_time": "2.575906223s",
        "declarations": 1659,
        "expressions": 61827,
        "functions": 1251,
        "inferenece_time": "8.230639067s",
        "item_collection_time": "16.754885647s",
        "modules": 132,
        "partial_unknown_types": 1667,
        "project_name": "./rustc-perf/collector/benchmarks/cargo/",
        "roots": 0,
        "total_time": "24.985546614s",
        "type_mismatches": 99,
        "unknown_types": 2689
    },
    {
        "crates": 63,
        "database_loaded_time": "793.693373ms",
        "declarations": 1660,
        "expressions": 92894,
        "functions": 1345,
        "inferenece_time": "6.388715823s",
        "item_collection_time": "5.639304027s",
        "modules": 134,
        "partial_unknown_types": 348,
        "project_name": "./rustc-perf/collector/benchmarks/clap-rs/",
        "roots": 0,
        "total_time": "12.02802875s",
        "type_mismatches": 31,
        "unknown_types": 829
    },
    {
        "crates": 18,
        "database_loaded_time": "1.148218617s",
        "declarations": 1883,
        "expressions": 91449,
        "functions": 1430,
        "inferenece_time": "6.085980539s",
        "item_collection_time": "9.362520524s",
        "modules": 140,
        "partial_unknown_types": 2486,
        "project_name": "./rustc-perf/collector/benchmarks/cranelift-codegen/",
        "roots": 0,
        "total_time": "15.448511263s",
        "type_mismatches": 30,
        "unknown_types": 1434
    },
    {
        "crates": 1,
        "database_loaded_time": "311.799927ms",
        "declarations": 504,
        "expressions": 8445,
        "functions": 257,
        "inferenece_time": "4.343341156s",
        "item_collection_time": "2.594133757s",
        "modules": 55,
        "partial_unknown_types": 791,
        "project_name": "./rustc-perf/collector/benchmarks/futures/",
        "roots": 0,
        "total_time": "6.937495813s",
        "type_mismatches": 17,
        "unknown_types": 488
    },
    {
        "crates": 1,
        "database_loaded_time": "118.465418ms",
        "declarations": 1,
        "expressions": 10,
        "functions": 1,
        "inferenece_time": "977.095591ms",
        "item_collection_time": "2.787089408s",
        "modules": 1,
        "partial_unknown_types": 0,
        "project_name": "./rustc-perf/collector/benchmarks/helloworld/",
        "roots": 0,
        "total_time": "3.764288899s",
        "type_mismatches": 0,
        "unknown_types": 0
    },
    {
        "crates": 2,
        "database_loaded_time": "1.055373367s",
        "declarations": 348,
        "expressions": 16088,
        "functions": 255,
        "inferenece_time": "2.807334574s",
        "item_collection_time": "9.760068761s",
        "modules": 28,
        "partial_unknown_types": 147,
        "project_name": "./rustc-perf/collector/benchmarks/html5ever/",
        "roots": 0,
        "total_time": "12.567412535s",
        "type_mismatches": 8,
        "unknown_types": 45
    },
    {
        "crates": 1,
        "database_loaded_time": "948.630199ms",
        "declarations": 1048,
        "expressions": 29500,
        "functions": 728,
        "inferenece_time": "4.347472508s",
        "item_collection_time": "9.472950805s",
        "modules": 126,
        "partial_unknown_types": 679,
        "project_name": "./rustc-perf/collector/benchmarks/hyper/",
        "roots": 0,
        "total_time": "13.820444513s",
        "type_mismatches": 15,
        "unknown_types": 171
    },
    {
        "crates": 1,
        "database_loaded_time": "979.903818ms",
        "declarations": 360,
        "expressions": 3185,
        "functions": 211,
        "inferenece_time": "1.988983742s",
        "item_collection_time": "10.369700437s",
        "modules": 36,
        "partial_unknown_types": 0,
        "project_name": "./rustc-perf/collector/benchmarks/syn/",
        "roots": 0,
        "total_time": "12.358694179s",
        "type_mismatches": 4,
        "unknown_types": 25
    }
]