[
    {
        "crates": 3,
        "database_loaded_time": "3.050508986s",
        "declarations": 3292,
        "expressions": 142230,
        "functions": 2763,
        "inferenece_time": "32.792252952s",
        "item_collection_time": "16.950872959s",
        "modules": 213,
        "partial_unknown_types": 2778,
        "project_name": "./rustc-perf/collector/benchmarks/cargo/",
        "roots": 128,
        "total_time": "49.743152311s",
        "type_mismatches": 200,
        "unknown_types": 2290
    },
    {
        "crates": 63,
        "database_loaded_time": "701.739987ms",
        "declarations": 1665,
        "expressions": 95616,
        "functions": 1351,
        "inferenece_time": "23.002842178s",
        "item_collection_time": "12.169274731s",
        "modules": 133,
        "partial_unknown_types": 3275,
        "project_name": "./rustc-perf/collector/benchmarks/clap-rs/",
        "roots": 73,
        "total_time": "35.172144709s",
        "type_mismatches": 94,
        "unknown_types": 2549
    },
    {
        "crates": 21,
        "database_loaded_time": "1.346433806s",
        "declarations": 3957,
        "expressions": 194999,
        "functions": 2993,
        "inferenece_time": "24.09904581s",
        "item_collection_time": "9.749029906s",
        "modules": 315,
        "partial_unknown_types": 11055,
        "project_name": "./rustc-perf/collector/benchmarks/cranelift-codegen/",
        "roots": 128,
        "total_time": "33.848084016s",
        "type_mismatches": 380,
        "unknown_types": 7395
    },
    {
        "crates": 1,
        "database_loaded_time": "262.784976ms",
        "declarations": 504,
        "expressions": 8434,
        "functions": 257,
        "inferenece_time": "6.358149238s",
        "item_collection_time": "2.527974164s",
        "modules": 55,
        "partial_unknown_types": 1546,
        "project_name": "./rustc-perf/collector/benchmarks/futures/",
        "roots": 12,
        "total_time": "8.886132102s",
        "type_mismatches": 28,
        "unknown_types": 637
    },
    {
        "crates": 1,
        "database_loaded_time": "86.528427ms",
        "declarations": 1,
        "expressions": 10,
        "functions": 1,
        "inferenece_time": "3.314007305s",
        "item_collection_time": "2.615489594s",
        "modules": 1,
        "partial_unknown_types": 0,
        "project_name": "./rustc-perf/collector/benchmarks/helloworld/",
        "roots": 11,
        "total_time": "5.929524299s",
        "type_mismatches": 0,
        "unknown_types": 0
    },
    {
        "crates": 2,
        "database_loaded_time": "2.064401093s",
        "declarations": 348,
        "expressions": 15683,
        "functions": 255,
        "inferenece_time": "10.852603338s",
        "item_collection_time": "8.514770069s",
        "modules": 28,
        "partial_unknown_types": 286,
        "project_name": "./rustc-perf/collector/benchmarks/html5ever/",
        "roots": 52,
        "total_time": "19.367405507s",
        "type_mismatches": 24,
        "unknown_types": 294
    },
    {
        "crates": 1,
        "database_loaded_time": "633.340043ms",
        "declarations": 1180,
        "expressions": 31448,
        "functions": 819,
        "inferenece_time": "13.591250541s",
        "item_collection_time": "8.088128444s",
        "modules": 167,
        "partial_unknown_types": 2142,
        "project_name": "./rustc-perf/collector/benchmarks/hyper/",
        "roots": 47,
        "total_time": "21.679404885s",
        "type_mismatches": 252,
        "unknown_types": 1058
    },
    {
        "crates": 9,
        "database_loaded_time": "651.947007ms",
        "declarations": 1244,
        "expressions": 21944,
        "functions": 995,
        "inferenece_time": "13.980840011s",
        "item_collection_time": "9.659347056s",
        "modules": 65,
        "partial_unknown_types": 2433,
        "project_name": "./rustc-perf/collector/benchmarks/syn/",
        "roots": 54,
        "total_time": "23.640213467s",
        "type_mismatches": 38,
        "unknown_types": 4121
    }
]